{
  "iso": "TW",
  "name": "Taiwan",
  "region": "APAC",
  "currency": "TWD",
  "language": "zh",
  "last_synced": "2026-05-01T04:02:40Z",
  "compliance": {
    "tax_filing": [],
    "vat_gst": [],
    "e_invoicing": [
      {
        "id": "TW-EUNI",
        "title": "Taiwan e-Unified Invoice",
        "summary": "Mandatory e-Unified Invoice for all VAT-registered businesses.",
        "status": "live",
        "effective_date": "2014-01-01",
        "source": "https://www.mof.gov.tw/",
        "source_type": "official",
        "first_seen": "2026-05-01T04:02:40Z",
        "last_updated": "2026-05-01T04:02:40Z"
      }
    ],
    "payroll": [],
    "local_gaap": [],
    "banking_payments": []
  }
}